langchain_zhipu/__init__.py
langchain_zhipu/__version__.py
langchain_zhipu/http/__init__.py
langchain_zhipu/http/api.py
langchain_zhipu/http/base.py
langchain_zhipu/http/chat.py
langchain_zhipu/http/embeddings.py
langchain_zhipu/http/enum.py
langchain_zhipu/http/env.py
langchain_zhipu/http/manager.py
langchain_zhipu/http/types.py
langchain_zhipu/utils.py
langchain_zhipu-4.1.8.dist-info/METADATA
langchain_zhipu-4.1.8.dist-info/WHEEL
langchain_zhipu-4.1.8.dist-info/RECORD
