Metadata-Version: 2.1
Name: langchain_zhipu
Version: 4.1.8
Summary: 将智谱AI集成到LangChain
Home-page: https://github.com/arcstep/langchain_zhipuai
License: MIT
Author: arcstep
Author-email: 43801@qq.com
Requires-Python: >=3.9,<4.0
Classifier: License :: OSI Approved :: MIT License
Classifier: Programming Language :: Python :: 3
Classifier: Programming Language :: Python :: 3.9
Classifier: Programming Language :: Python :: 3.10
Classifier: Programming Language :: Python :: 3.11
Classifier: Programming Language :: Python :: 3.12
Requires-Dist: cachetools (==4.2.2)
Requires-Dist: httpx (>=0.23.0,<0.24.0)
Requires-Dist: langchain (>=0.1.20,<0.3.0)
Requires-Dist: langchain-community (>=0.0.38,<0.3.0)
Requires-Dist: pydantic (>=1,<3)
Requires-Dist: pyjwt (>=2.8.0,<3.0.0)
Requires-Dist: regex (>=2024.4.16,<2025.0.0)
Requires-Dist: tiktoken (>=0.7.0,<0.8.0)
Requires-Dist: tqdm (>=4.66.2,<5.0.0)
Project-URL: Repository, https://github.com/arcstep/langchain_zhipuai.git
